forwardAlert4/__init__.py
forwardAlert4/__main__.py
forwardAlert4/alerts.py
forwardAlert4/requirements.txt
forwardAlert4/runs.py
Alerts4-0.0.5.dist-info/LICENSE
Alerts4-0.0.5.dist-info/METADATA
Alerts4-0.0.5.dist-info/WHEEL
Alerts4-0.0.5.dist-info/entry_points.txt
Alerts4-0.0.5.dist-info/top_level.txt
Alerts4-0.0.5.dist-info/RECORD
